metatree/__init__.py
metatree/decision_tree_class.py
metatree/eval_generalization.py
metatree/eval_generalization_cart.py
metatree/eval_generalization_gosdt.py
metatree/generate_util.py
metatree/model_metatree.py
metatree/modeling_outputs.py
metatree/run_train.py
metatree/utils.py
metatree/scripts/__init__.py
metatree/scripts/datagen_nxor_bound.py
metatreelib-0.1.1.dist-info/LICENSE
metatreelib-0.1.1.dist-info/METADATA
metatreelib-0.1.1.dist-info/WHEEL
metatreelib-0.1.1.dist-info/top_level.txt
metatreelib-0.1.1.dist-info/RECORD
