Metadata-Version: 2.1
Name: metatreelib
Version: 0.1.1
Summary: PyTorch Implementation for MetaTree: Learning a Decision Tree Algorithm with Transformers
Home-page: https://github.com/EvanZhuang/MetaTree
Author: Yufan Zhuang, Lucas Liu, Chandan Singh, Jingbo Shang, Jianfeng Gao
Author-email: y5zhuang@ucsd.edu
Classifier: Programming Language :: Python :: 3
Classifier: Programming Language :: Python :: 3.7
Classifier: Programming Language :: Python :: 3.8
Classifier: Programming Language :: Python :: 3.9
Classifier: Programming Language :: Python :: 3.10
Classifier: License :: OSI Approved :: MIT License
Classifier: Operating System :: OS Independent
Classifier: Topic :: Scientific/Engineering :: Artificial Intelligence
Requires-Python: >=3.7.0
License-File: LICENSE
Requires-Dist: transformers ==4.34.0
Requires-Dist: datasets
Requires-Dist: scikit-learn
Requires-Dist: evaluate
Requires-Dist: accelerate
Requires-Dist: matplotlib
Requires-Dist: tqdm
Requires-Dist: huggingface-hub
Requires-Dist: wandb
Requires-Dist: einops
Requires-Dist: deepspeed
